resolver/__init__.py
resolver/exceptions.py
resolver/ssm.py
sceptre_ssm_resolver-1.2.2.dist-info/METADATA
sceptre_ssm_resolver-1.2.2.dist-info/WHEEL
sceptre_ssm_resolver-1.2.2.dist-info/entry_points.txt
sceptre_ssm_resolver-1.2.2.dist-info/top_level.txt
sceptre_ssm_resolver-1.2.2.dist-info/RECORD
